gravilab/__init__.py
gravilab/base/__init__.py
gravilab/base/seismometer.py
gravilab/base/system_element.py
gravilab/formats/__init__.py
gravilab/formats/seismic_time_series.py
gravilab/formats/spectrum.py
gravilab/input/__init__.py
gravilab/input/data_reader.py
gravilab/open.py
gravilab-0.1.4.dist-info/LICENSE.txt
gravilab-0.1.4.dist-info/WHEEL
gravilab-0.1.4.dist-info/METADATA
gravilab-0.1.4.dist-info/RECORD
