Metadata-Version: 2.1
Name: gravilab
Version: 0.1.4
Summary: Package to analyze seismic data based on obspy and spicypy packages.
Home-page: https://gitlab.com/pyda-group/gravilab
Author: Artem Basalaev
Author-email: artemDOTbasalaev@physikDOTuni-hamburg.de
Requires-Python: >=3.8,<3.14
Classifier: Programming Language :: Python :: 3
Classifier: Programming Language :: Python :: 3.8
Classifier: Programming Language :: Python :: 3.9
Classifier: Programming Language :: Python :: 3.10
Classifier: Programming Language :: Python :: 3.11
Requires-Dist: importlib-metadata (>=1.1.3) ; python_full_version <= "3.7.0"
Requires-Dist: numpy (>=1.26.4)
Requires-Dist: obspy (>=1.4.1,<2.0.0)
Requires-Dist: pandas (>=1.1)
Requires-Dist: spicypy (>=0.8)
Project-URL: Repository, https://gitlab.com/pyda-group/gravilab
